components/dff4/dff4.sv
module dff4(
  input logic clk,
  input logic [3:0] D,
  output logic [3:0] Q
);
  always_ff @(posedge clk) begin
    for (int i = 0; i < 4; i++) begin
      Q[i] <= D[i];
    end
  end
endmodule: dff4

components/arithmetic/halfadder.sv
module halfadder(
  input logic A, B,
  output logic S, C
);
  assign S = A ^ B;
  assign C = A & B;
endmodule: halfadder;

components/arithmetic/fulladder.sv
module fulladder(
  input logic A, B, CIN,
  output logic COUT, S
);
  logic COUT1, COUT2, SUM1;

  halfadder ha1 ( .A(A), .B(B), .C(COUT1), .S(SUM1) );
  halfadder ha2 ( .A(SUM1), .B(CIN), .C(COUT2), .S(S) );

  assign COUT = COUT1 | COUT2;
endmodule: fulladder;

components/arithmetic/ripplecarryadder.sv
module ripplecarryadder(
  input logic [3:0] A,
  input logic [3:0] B,
  input logic CIN,
  output logic [3:0] S,
  output logic COUT
);
  logic [4:0] carry;
  assign carry[0] = CIN;

  genvar i;
  generate
    for (i = 0; i < 4; i++) begin
      fulladder fa (
        .A(A[i]),
        .B(B[i]),
        .CIN(carry[i]),
        .S(S[i]),
        .COUT(carry[i+1])
      );
    end
  endgenerate

  assign COUT = carry[4];
endmodule: ripplecarryadder

components/counter/counter.sv
module counter(
  input logic clk,
  output logic [3:0] Q
);
  logic [3:0] SD;
  
  ripplecarryadder rca (
    .A(Q),
    .B(4'd1),
    .CIN(1'd0),
    .S(SD),
    .COUT()
  );
  
  dff4 dff (
    .D(SD),
    .Q(Q),
    .clk(clk)
  );
endmodule: counter

components/counter/tb.sv
module tb();
  logic clk;
  logic [3:0] Q;

  counter dut (
    .clk(clk),
    .Q(Q)
  );

  initial begin
    clk = 0;
    forever #5 clk = !clk;
  end

  initial begin
   #100;
   $finish();
  end

  initial begin
    $dumpfile("dump.vcd");
    $dumpvars;
  end
endmodule: tb

components/counter/dump.vcd
$version Generated by VerilatedVcd $end
$timescale 1ps $end
 $scope module TOP $end
  $scope module tb $end
   $var wire 1 2 clk $end
   $var wire 4 # Q [3:0] $end
   $scope module dut $end
    $var wire 1 2 clk $end
    $var wire 4 # Q [3:0] $end
    $var wire 4 $ SD [3:0] $end
    $scope module dff $end
     $var wire 1 2 clk $end
     $var wire 4 $ D [3:0] $end
     $var wire 4 # Q [3:0] $end
     $scope module unnamedblk1 $end
      $var wire 32 % i [31:0] $end
     $upscope $end
    $upscope $end
    $scope module rca $end
     $var wire 4 # A [3:0] $end
     $var wire 4 3 B [3:0] $end
     $var wire 1 4 CIN $end
     $var wire 4 $ S [3:0] $end
     $var wire 1 & COUT $end
     $var wire 5 ' carry [4:0] $end
     $scope module genblk1[0] $end
      $scope module fa $end
       $var wire 1 ( A $end
       $var wire 1 5 B $end
       $var wire 1 4 CIN $end
       $var wire 1 ( COUT $end
       $var wire 1 ) S $end
       $var wire 1 ( COUT1 $end
       $var wire 1 4 COUT2 $end
       $var wire 1 ) SUM1 $end
       $scope module ha1 $end
        $var wire 1 ( A $end
        $var wire 1 5 B $end
        $var wire 1 ) S $end
        $var wire 1 ( C $end
       $upscope $end
       $scope module ha2 $end
        $var wire 1 ) A $end
        $var wire 1 4 B $end
        $var wire 1 ) S $end
        $var wire 1 4 C $end
       $upscope $end
      $upscope $end
     $upscope $end
     $scope module genblk1[1] $end
      $scope module fa $end
       $var wire 1 * A $end
       $var wire 1 4 B $end
       $var wire 1 ( CIN $end
       $var wire 1 + COUT $end
       $var wire 1 , S $end
       $var wire 1 4 COUT1 $end
       $var wire 1 + COUT2 $end
       $var wire 1 * SUM1 $end
       $scope module ha1 $end
        $var wire 1 * A $end
        $var wire 1 4 B $end
        $var wire 1 * S $end
        $var wire 1 4 C $end
       $upscope $end
       $scope module ha2 $end
        $var wire 1 * A $end
        $var wire 1 ( B $end
        $var wire 1 , S $end
        $var wire 1 + C $end
       $upscope $end
      $upscope $end
     $upscope $end
     $scope module genblk1[2] $end
      $scope module fa $end
       $var wire 1 - A $end
       $var wire 1 4 B $end
       $var wire 1 + CIN $end
       $var wire 1 . COUT $end
       $var wire 1 / S $end
       $var wire 1 4 COUT1 $end
       $var wire 1 . COUT2 $end
       $var wire 1 - SUM1 $end
       $scope module ha1 $end
        $var wire 1 - A $end
        $var wire 1 4 B $end
        $var wire 1 - S $end
        $var wire 1 4 C $end
       $upscope $end
       $scope module ha2 $end
        $var wire 1 - A $end
        $var wire 1 + B $end
        $var wire 1 / S $end
        $var wire 1 . C $end
       $upscope $end
      $upscope $end
     $upscope $end
     $scope module genblk1[3] $end
      $scope module fa $end
       $var wire 1 0 A $end
       $var wire 1 4 B $end
       $var wire 1 . CIN $end
       $var wire 1 & COUT $end
       $var wire 1 1 S $end
       $var wire 1 4 COUT1 $end
       $var wire 1 & COUT2 $end
       $var wire 1 0 SUM1 $end
       $scope module ha1 $end
        $var wire 1 0 A $end
        $var wire 1 4 B $end
        $var wire 1 0 S $end
        $var wire 1 4 C $end
       $upscope $end
       $scope module ha2 $end
        $var wire 1 0 A $end
        $var wire 1 . B $end
        $var wire 1 1 S $end
        $var wire 1 & C $end
       $upscope $end
      $upscope $end
     $upscope $end
    $upscope $end
   $upscope $end
  $upscope $end
 $upscope $end
$enddefinitions $end


#0
b0000 #
b0001 $
b00000000000000000000000000000000 %
0&
b00000 '
0(
1)
0*
0+
0,
0-
0.
0/
00
01
02
b0001 3
04
15
#5
b0001 #
b0010 $
b00000000000000000000000000000100 %
b00010 '
1(
0)
1,
12
#10
02
#15
b0010 #
b0011 $
b00000 '
0(
1)
1*
12
#20
02
#25
b0011 #
b0100 $
b00110 '
1(
0)
1+
0,
1/
12
#30
02
#35
b0100 #
b0101 $
b00000 '
0(
1)
0*
0+
1-
12
#40
02
#45
b0101 #
b0110 $
b00010 '
1(
0)
1,
12
#50
02
#55
b0110 #
b0111 $
b00000 '
0(
1)
1*
12
#60
02
#65
b0111 #
b1000 $
b01110 '
1(
0)
1+
0,
1.
0/
11
12
#70
02
#75
b1000 #
b1001 $
b00000 '
0(
1)
0*
0+
0-
0.
10
12
#80
02
#85
b1001 #
b1010 $
b00010 '
1(
0)
1,
12
#90
02
#95
b1010 #
b1011 $
b00000 '
0(
1)
1*
12
