components/rom/rom.sv
module rom #(
  parameter int ADDR_WIDTH = 4,
  parameter int DATA_WIDTH = 8,
  parameter logic [DATA_WIDTH-1:0] INIT_DATA [2**ADDR_WIDTH] = '{default: 0}
)(
  input logic clk,
  input logic [ADDR_WIDTH-1:0] ADDR,
  output logic [DATA_WIDTH-1:0] DOUT
);
  logic [DATA_WIDTH-1:0] storage [2**ADDR_WIDTH];

  initial begin
    storage = INIT_DATA;
  end

  always_ff @(posedge clk) begin : readout
    DOUT <= INIT_DATA[ADDR];
  end
endmodule: rom

components/rom/tb.sv
module tb();
  logic clk;
  logic [3:0] ADDR;
  logic [7:0] DOUT;

  rom #(
    .INIT_DATA('{0: 8'd70, 1: 8'd80, 2: 8'd71, 3: 8'd65, default: 8'd0}) // FPGA
  ) dut (
    .clk(clk),
    .ADDR(ADDR),
    .DOUT(DOUT)
  );

  initial begin
    clk = 0;
    forever #5 clk = !clk;
  end

  initial begin
    for (logic [3:0] i = 0; i < 5; i++) begin
      ADDR = i;
      #10;
    end

    $finish();
  end

  initial begin
    $dumpfile("dump.vcd");
    $dumpvars;
  end
endmodule: tb

components/rom/dump.vcd
$version Generated by VerilatedVcd $end
$timescale 1ps $end
 $scope module TOP $end
  $scope module tb $end
   $var wire 1 3 clk $end
   $var wire 4 4 ADDR [3:0] $end
   $var wire 8 5 DOUT [7:0] $end
   $scope module dut $end
    $var wire 32 7 ADDR_WIDTH [31:0] $end
    $var wire 32 8 DATA_WIDTH [31:0] $end
    $var wire 8 9 INIT_DATA[0] [7:0] $end
    $var wire 8 : INIT_DATA[1] [7:0] $end
    $var wire 8 ; INIT_DATA[2] [7:0] $end
    $var wire 8 < INIT_DATA[3] [7:0] $end
    $var wire 8 = INIT_DATA[4] [7:0] $end
    $var wire 8 > INIT_DATA[5] [7:0] $end
    $var wire 8 ? INIT_DATA[6] [7:0] $end
    $var wire 8 @ INIT_DATA[7] [7:0] $end
    $var wire 8 A INIT_DATA[8] [7:0] $end
    $var wire 8 B INIT_DATA[9] [7:0] $end
    $var wire 8 C INIT_DATA[10] [7:0] $end
    $var wire 8 D INIT_DATA[11] [7:0] $end
    $var wire 8 E INIT_DATA[12] [7:0] $end
    $var wire 8 F INIT_DATA[13] [7:0] $end
    $var wire 8 G INIT_DATA[14] [7:0] $end
    $var wire 8 H INIT_DATA[15] [7:0] $end
    $var wire 1 3 clk $end
    $var wire 4 4 ADDR [3:0] $end
    $var wire 8 5 DOUT [7:0] $end
    $var wire 8 # storage[0] [7:0] $end
    $var wire 8 $ storage[1] [7:0] $end
    $var wire 8 % storage[2] [7:0] $end
    $var wire 8 & storage[3] [7:0] $end
    $var wire 8 ' storage[4] [7:0] $end
    $var wire 8 ( storage[5] [7:0] $end
    $var wire 8 ) storage[6] [7:0] $end
    $var wire 8 * storage[7] [7:0] $end
    $var wire 8 + storage[8] [7:0] $end
    $var wire 8 , storage[9] [7:0] $end
    $var wire 8 - storage[10] [7:0] $end
    $var wire 8 . storage[11] [7:0] $end
    $var wire 8 / storage[12] [7:0] $end
    $var wire 8 0 storage[13] [7:0] $end
    $var wire 8 1 storage[14] [7:0] $end
    $var wire 8 2 storage[15] [7:0] $end
   $upscope $end
   $scope module unnamedblk1 $end
    $var wire 4 6 i [3:0] $end
   $upscope $end
  $upscope $end
 $upscope $end
$enddefinitions $end


#0
b01000110 #
b01010000 $
b01000111 %
b01000001 &
b00000000 '
b00000000 (
b00000000 )
b00000000 *
b00000000 +
b00000000 ,
b00000000 -
b00000000 .
b00000000 /
b00000000 0
b00000000 1
b00000000 2
03
b0000 4
b00000000 5
b0000 6
b00000000000000000000000000000100 7
b00000000000000000000000000001000 8
b01000110 9
b01010000 :
b01000111 ;
b01000001 <
b00000000 =
b00000000 >
b00000000 ?
b00000000 @
b00000000 A
b00000000 B
b00000000 C
b00000000 D
b00000000 E
b00000000 F
b00000000 G
b00000000 H
#5
13
b01000110 5
#10
03
b0001 4
b0001 6
#15
13
b01010000 5
#20
03
b0010 4
b0010 6
#25
13
b01000111 5
#30
03
b0011 4
b0011 6
#35
13
b01000001 5
#40
03
b0100 4
b0100 6
#45
13
b00000000 5
#50
03
b0101 6
