circuits/countdowntimer/countdowntimer.sv
module nor4(
  input logic [3:0] A,
  output logic OUT
);
  assign OUT = !(A[0] | A[1] | A[2] | A[3]);
endmodule: nor4

module countdowntimer(
  input clk,
  input logic [3:0] D,
  output logic [3:0] Q
);
  logic CONTROL;
  logic [3:0] YD, SA;

  ripplecarryadder rca (
    .A(Q),
    .B(4'b1111),
    .CIN(0),
    .S(SA),
    .COUT()
  );

  mux2x4 mux (
    .A(SA),
    .B(D),
    .S(CONTROL),
    .Y(YD)
  );

  dff4 dff (
    .D(YD),
    .Q(Q),
    .clk(clk)
  );

  nor4 n (
    .A(Q),
    .OUT(CONTROL)
  );
endmodule: countdowntimer

components/dff4/dff4.sv
module dff4(
  input logic clk,
  input logic [3:0] D,
  output logic [3:0] Q
);
  always_ff @(posedge clk) begin
    for (int i = 0; i < 4; i++) begin
      Q[i] <= D[i];
    end
  end
endmodule: dff4

components/mux2/mux2.sv
module mux2(input S, A, B, output Y);
  assign Y = S ? B : A;
endmodule: mux2

components/mux2x4/mux2x4.sv
module mux2x4(
  input logic [3:0] A,
  input logic [3:0] B,
  input logic S,
  output logic [3:0] Y
);

  genvar i;
  generate
    for (i = 0; i < 4; i++) begin : gen_muxes
      mux2 mux(
        .A(A[i]),
        .B(B[i]),
        .S(S),
        .Y(Y[i])
      );
    end
  endgenerate

endmodule: mux2x4

components/arithmetic/halfadder.sv
module halfadder(
  input logic A, B,
  output logic S, C
);
  assign S = A ^ B;
  assign C = A & B;
endmodule: halfadder;

components/arithmetic/fulladder.sv
module fulladder(
  input logic A, B, CIN,
  output logic COUT, S
);
  logic COUT1, COUT2, SUM1;

  halfadder ha1 ( .A(A), .B(B), .C(COUT1), .S(SUM1) );
  halfadder ha2 ( .A(SUM1), .B(CIN), .C(COUT2), .S(S) );

  assign COUT = COUT1 | COUT2;
endmodule: fulladder;

components/arithmetic/ripplecarryadder.sv
module ripplecarryadder(
  input logic [3:0] A,
  input logic [3:0] B,
  input logic CIN,
  output logic [3:0] S,
  output logic COUT
);
  logic [4:0] carry;
  assign carry[0] = CIN;

  genvar i;
  generate
    for (i = 0; i < 4; i++) begin
      fulladder fa (
        .A(A[i]),
        .B(B[i]),
        .CIN(carry[i]),
        .S(S[i]),
        .COUT(carry[i+1])
      );
    end
  endgenerate

  assign COUT = carry[4];
endmodule: ripplecarryadder

circuits/countdowntimer/tb.sv
module tb();
  logic clk;
  logic [3:0] D, Q;

  countdowntimer dut (
    .clk(clk),
    .D(D),
    .Q(Q)
  );

  initial begin
    clk = 0;
    forever #5 clk = !clk;
  end

  initial begin
    D = 4'd8;
    #300;
    $finish();
  end

  initial begin
    $dumpfile("dump.vcd");
    $dumpvars;
  end
endmodule: tb 

module tb_nor();
  logic Q;
  logic [3:0] A = 4'b0101;

  nor4 n (
    .A(A),
    .OUT(Q)
  );

  initial begin
    #1;
    A = 4'b0000;
    #1
    A = 4'b0100;
    #1
    $finish();
  end

  initial begin
    $dumpfile("dump.vcd");
    $dumpvars;
  end

endmodule: tb_nor

circuits/countdowntimer/dump.vcd
$version Generated by VerilatedVcd $end
$timescale 1ps $end
 $scope module TOP $end
  $scope module tb $end
   $var wire 1 > clk $end
   $var wire 4 # D [3:0] $end
   $var wire 4 ( Q [3:0] $end
   $scope module dut $end
    $var wire 1 > clk $end
    $var wire 4 # D [3:0] $end
    $var wire 4 ( Q [3:0] $end
    $var wire 1 ) CONTROL $end
    $var wire 4 ? YD [3:0] $end
    $var wire 4 * SA [3:0] $end
    $scope module dff $end
     $var wire 1 > clk $end
     $var wire 4 ? D [3:0] $end
     $var wire 4 ( Q [3:0] $end
     $scope module unnamedblk1 $end
      $var wire 32 + i [31:0] $end
     $upscope $end
    $upscope $end
    $scope module mux $end
     $var wire 4 * A [3:0] $end
     $var wire 4 # B [3:0] $end
     $var wire 1 ) S $end
     $var wire 4 ? Y [3:0] $end
     $scope module gen_muxes[0] $end
      $scope module mux $end
       $var wire 1 ) S $end
       $var wire 1 , A $end
       $var wire 1 $ B $end
       $var wire 1 @ Y $end
      $upscope $end
     $upscope $end
     $scope module gen_muxes[1] $end
      $scope module mux $end
       $var wire 1 ) S $end
       $var wire 1 - A $end
       $var wire 1 % B $end
       $var wire 1 A Y $end
      $upscope $end
     $upscope $end
     $scope module gen_muxes[2] $end
      $scope module mux $end
       $var wire 1 ) S $end
       $var wire 1 . A $end
       $var wire 1 & B $end
       $var wire 1 B Y $end
      $upscope $end
     $upscope $end
     $scope module gen_muxes[3] $end
      $scope module mux $end
       $var wire 1 ) S $end
       $var wire 1 / A $end
       $var wire 1 ' B $end
       $var wire 1 C Y $end
      $upscope $end
     $upscope $end
    $upscope $end
    $scope module n $end
     $var wire 4 ( A [3:0] $end
     $var wire 1 ) OUT $end
    $upscope $end
    $scope module rca $end
     $var wire 4 ( A [3:0] $end
     $var wire 4 D B [3:0] $end
     $var wire 1 E CIN $end
     $var wire 4 * S [3:0] $end
     $var wire 1 0 COUT $end
     $var wire 5 1 carry [4:0] $end
     $scope module genblk1[0] $end
      $scope module fa $end
       $var wire 1 2 A $end
       $var wire 1 F B $end
       $var wire 1 E CIN $end
       $var wire 1 2 COUT $end
       $var wire 1 , S $end
       $var wire 1 2 COUT1 $end
       $var wire 1 E COUT2 $end
       $var wire 1 , SUM1 $end
       $scope module ha1 $end
        $var wire 1 2 A $end
        $var wire 1 F B $end
        $var wire 1 , S $end
        $var wire 1 2 C $end
       $upscope $end
       $scope module ha2 $end
        $var wire 1 , A $end
        $var wire 1 E B $end
        $var wire 1 , S $end
        $var wire 1 E C $end
       $upscope $end
      $upscope $end
     $upscope $end
     $scope module genblk1[1] $end
      $scope module fa $end
       $var wire 1 3 A $end
       $var wire 1 F B $end
       $var wire 1 2 CIN $end
       $var wire 1 4 COUT $end
       $var wire 1 - S $end
       $var wire 1 3 COUT1 $end
       $var wire 1 5 COUT2 $end
       $var wire 1 6 SUM1 $end
       $scope module ha1 $end
        $var wire 1 3 A $end
        $var wire 1 F B $end
        $var wire 1 6 S $end
        $var wire 1 3 C $end
       $upscope $end
       $scope module ha2 $end
        $var wire 1 6 A $end
        $var wire 1 2 B $end
        $var wire 1 - S $end
        $var wire 1 5 C $end
       $upscope $end
      $upscope $end
     $upscope $end
     $scope module genblk1[2] $end
      $scope module fa $end
       $var wire 1 7 A $end
       $var wire 1 F B $end
       $var wire 1 4 CIN $end
       $var wire 1 8 COUT $end
       $var wire 1 . S $end
       $var wire 1 7 COUT1 $end
       $var wire 1 9 COUT2 $end
       $var wire 1 : SUM1 $end
       $scope module ha1 $end
        $var wire 1 7 A $end
        $var wire 1 F B $end
        $var wire 1 : S $end
        $var wire 1 7 C $end
       $upscope $end
       $scope module ha2 $end
        $var wire 1 : A $end
        $var wire 1 4 B $end
        $var wire 1 . S $end
        $var wire 1 9 C $end
       $upscope $end
      $upscope $end
     $upscope $end
     $scope module genblk1[3] $end
      $scope module fa $end
       $var wire 1 ; A $end
       $var wire 1 F B $end
       $var wire 1 8 CIN $end
       $var wire 1 0 COUT $end
       $var wire 1 / S $end
       $var wire 1 ; COUT1 $end
       $var wire 1 < COUT2 $end
       $var wire 1 = SUM1 $end
       $scope module ha1 $end
        $var wire 1 ; A $end
        $var wire 1 F B $end
        $var wire 1 = S $end
        $var wire 1 ; C $end
       $upscope $end
       $scope module ha2 $end
        $var wire 1 = A $end
        $var wire 1 8 B $end
        $var wire 1 / S $end
        $var wire 1 < C $end
       $upscope $end
      $upscope $end
     $upscope $end
    $upscope $end
   $upscope $end
  $upscope $end
 $upscope $end
$enddefinitions $end


#0
b1000 #
0$
0%
0&
1'
b0000 (
1)
b1111 *
b00000000000000000000000000000000 +
1,
1-
1.
1/
00
b00000 1
02
03
04
05
16
07
08
09
1:
0;
0<
1=
0>
b1000 ?
0@
0A
0B
1C
b1111 D
0E
1F
#5
b1000 (
0)
b0111 *
b00000000000000000000000000000100 +
0/
10
b10000 1
1;
0=
1>
b0111 ?
1@
1A
1B
0C
#10
0>
#15
b0111 (
b0110 *
0,
b11110 1
12
13
14
06
17
18
0:
0;
1<
1=
1>
b0110 ?
0@
#20
0>
#25
b0110 (
b0101 *
1,
0-
b11100 1
02
1>
b0101 ?
1@
0A
#30
0>
#35
b0101 (
b0100 *
0,
b11110 1
12
03
15
16
1>
b0100 ?
0@
#40
0>
#45
b0100 (
b0011 *
1,
1-
0.
b11000 1
02
04
05
1>
b0011 ?
1@
1A
0B
#50
0>
#55
b0011 (
b0010 *
0,
b11110 1
12
13
14
06
07
19
1:
1>
b0010 ?
0@
#60
0>
#65
b0010 (
b0001 *
1,
0-
b11100 1
02
1>
b0001 ?
1@
0A
#70
0>
#75
b0001 (
b0000 *
0,
b11110 1
12
03
15
16
1>
b0000 ?
0@
#80
0>
#85
b0000 (
1)
b1111 *
1,
1-
1.
1/
00
b00000 1
02
04
05
08
09
0<
1>
b1000 ?
1C
#90
0>
#95
b1000 (
0)
b0111 *
0/
10
b10000 1
1;
0=
1>
b0111 ?
1@
1A
1B
0C
#100
0>
#105
b0111 (
b0110 *
0,
b11110 1
12
13
14
06
17
18
0:
0;
1<
1=
1>
b0110 ?
0@
#110
0>
#115
b0110 (
b0101 *
1,
0-
b11100 1
02
1>
b0101 ?
1@
0A
#120
0>
#125
b0101 (
b0100 *
0,
b11110 1
12
03
15
16
1>
b0100 ?
0@
#130
0>
#135
b0100 (
b0011 *
1,
1-
0.
b11000 1
02
04
05
1>
b0011 ?
1@
1A
0B
#140
0>
#145
b0011 (
b0010 *
0,
b11110 1
12
13
14
06
07
19
1:
1>
b0010 ?
0@
#150
0>
#155
b0010 (
b0001 *
1,
0-
b11100 1
02
1>
b0001 ?
1@
0A
#160
0>
#165
b0001 (
b0000 *
0,
b11110 1
12
03
15
16
1>
b0000 ?
0@
#170
0>
#175
b0000 (
1)
b1111 *
1,
1-
1.
1/
00
b00000 1
02
04
05
08
09
0<
1>
b1000 ?
1C
#180
0>
#185
b1000 (
0)
b0111 *
0/
10
b10000 1
1;
0=
1>
b0111 ?
1@
1A
1B
0C
#190
0>
#195
b0111 (
b0110 *
0,
b11110 1
12
13
14
06
17
18
0:
0;
1<
1=
1>
b0110 ?
0@
#200
0>
#205
b0110 (
b0101 *
1,
0-
b11100 1
02
1>
b0101 ?
1@
0A
#210
0>
#215
b0101 (
b0100 *
0,
b11110 1
12
03
15
16
1>
b0100 ?
0@
#220
0>
#225
b0100 (
b0011 *
1,
1-
0.
b11000 1
02
04
05
1>
b0011 ?
1@
1A
0B
#230
0>
#235
b0011 (
b0010 *
0,
b11110 1
12
13
14
06
07
19
1:
1>
b0010 ?
0@
#240
0>
#245
b0010 (
b0001 *
1,
0-
b11100 1
02
1>
b0001 ?
1@
0A
#250
0>
#255
b0001 (
b0000 *
0,
b11110 1
12
03
15
16
1>
b0000 ?
0@
#260
0>
#265
b0000 (
1)
b1111 *
1,
1-
1.
1/
00
b00000 1
02
04
05
08
09
0<
1>
b1000 ?
1C
#270
0>
#275
b1000 (
0)
b0111 *
0/
10
b10000 1
1;
0=
1>
b0111 ?
1@
1A
1B
0C
#280
0>
#285
b0111 (
b0110 *
0,
b11110 1
12
13
14
06
17
18
0:
0;
1<
1=
1>
b0110 ?
0@
#290
0>
#295
b0110 (
b0101 *
1,
0-
b11100 1
02
1>
b0101 ?
1@
0A
