components/mux2/mux2.sv
module mux2(input S, A, B, output Y);
  assign Y = S ? B : A;
endmodule: mux2

components/mux2x4/mux2x4.sv
module mux2x4(
  input logic [3:0] A,
  input logic [3:0] B,
  input logic S,
  output logic [3:0] Y
);

  genvar i;
  generate
    for (i = 0; i < 4; i++) begin : gen_muxes
      mux2 mux(
        .A(A[i]),
        .B(B[i]),
        .S(S),
        .Y(Y[i])
      );
    end
  endgenerate

endmodule: mux2x4

components/mux2x4/tb.sv
module tb();
  logic [3:0] A, B, Y;
  logic S;

  mux2x4 m(
    .A(A),
    .B(B),
    .S(S),
    .Y(Y)
  );

  initial begin
    A = 4'b0001;
    B = 4'b1110;
    S = 0;

    #1
    S = 1;

    #1
    A = 4'b0010;
    B = 4'b1101;
    S = 0;

    #1
    S = 1;

    #1
    A = 4'b0100;
    B = 4'b1011;
    S = 0;

    #1
    S = 1;

    #1
    A = 4'b1000;
    B = 4'b0111;
    S = 0;

    #1
    S = 1;
  end

  initial begin
    $dumpfile("dump.vcd");
    $dumpvars;
  end
endmodule: tb

components/mux2x4/dump.vcd
$version Generated by VerilatedVcd $end
$timescale 1ps $end
 $scope module TOP $end
  $scope module tb $end
   $var wire 4 # A [3:0] $end
   $var wire 4 $ B [3:0] $end
   $var wire 4 % Y [3:0] $end
   $var wire 1 & S $end
   $scope module m $end
    $var wire 4 # A [3:0] $end
    $var wire 4 $ B [3:0] $end
    $var wire 1 & S $end
    $var wire 4 % Y [3:0] $end
    $scope module gen_muxes[0] $end
     $scope module mux $end
      $var wire 1 & S $end
      $var wire 1 ' A $end
      $var wire 1 ( B $end
      $var wire 1 ) Y $end
     $upscope $end
    $upscope $end
    $scope module gen_muxes[1] $end
     $scope module mux $end
      $var wire 1 & S $end
      $var wire 1 * A $end
      $var wire 1 + B $end
      $var wire 1 , Y $end
     $upscope $end
    $upscope $end
    $scope module gen_muxes[2] $end
     $scope module mux $end
      $var wire 1 & S $end
      $var wire 1 - A $end
      $var wire 1 . B $end
      $var wire 1 / Y $end
     $upscope $end
    $upscope $end
    $scope module gen_muxes[3] $end
     $scope module mux $end
      $var wire 1 & S $end
      $var wire 1 0 A $end
      $var wire 1 1 B $end
      $var wire 1 2 Y $end
     $upscope $end
    $upscope $end
   $upscope $end
  $upscope $end
 $upscope $end
$enddefinitions $end


#0
b0001 #
b1110 $
b0001 %
0&
1'
0(
1)
0*
1+
0,
0-
1.
0/
00
11
02
#1
b1110 %
1&
0)
1,
1/
12
#2
b0010 #
b1101 $
b0010 %
0&
0'
1(
1*
0+
0/
02
#3
b1101 %
1&
1)
0,
1/
12
#4
b0100 #
b1011 $
b0100 %
0&
0)
0*
1+
1-
0.
02
#5
b1011 %
1&
1)
1,
0/
12
#6
b1000 #
b0111 $
b1000 %
0&
0)
0,
0-
1.
10
01
#7
b0111 %
1&
1)
1,
1/
02
