components/dff4/dff4.sv
module dff4(
  input logic clk,
  input logic [3:0] D,
  output logic [3:0] Q
);
  always_ff @(posedge clk) begin
    for (int i = 0; i < 4; i++) begin
      Q[i] <= D[i];
    end
  end
endmodule: dff4

components/mux2/mux2.sv
module mux2(input S, A, B, output Y);
  assign Y = S ? B : A;
endmodule: mux2

components/mux2x4/mux2x4.sv
module mux2x4(
  input logic [3:0] A,
  input logic [3:0] B,
  input logic S,
  output logic [3:0] Y
);

  genvar i;
  generate
    for (i = 0; i < 4; i++) begin : gen_muxes
      mux2 mux(
        .A(A[i]),
        .B(B[i]),
        .S(S),
        .Y(Y[i])
      );
    end
  endgenerate

endmodule: mux2x4

components/arithmetic/halfadder.sv
module halfadder(
  input logic A, B,
  output logic S, C
);
  assign S = A ^ B;
  assign C = A & B;
endmodule: halfadder;

components/arithmetic/fulladder.sv
module fulladder(
  input logic A, B, CIN,
  output logic COUT, S
);
  logic COUT1, COUT2, SUM1;

  halfadder ha1 ( .A(A), .B(B), .C(COUT1), .S(SUM1) );
  halfadder ha2 ( .A(SUM1), .B(CIN), .C(COUT2), .S(S) );

  assign COUT = COUT1 | COUT2;
endmodule: fulladder;

components/arithmetic/ripplecarryadder.sv
module ripplecarryadder(
  input logic [3:0] A,
  input logic [3:0] B,
  input logic CIN,
  output logic [3:0] S,
  output logic COUT
);
  logic [4:0] carry;
  assign carry[0] = CIN;

  genvar i;
  generate
    for (i = 0; i < 4; i++) begin
      fulladder fa (
        .A(A[i]),
        .B(B[i]),
        .CIN(carry[i]),
        .S(S[i]),
        .COUT(carry[i+1])
      );
    end
  endgenerate

  assign COUT = carry[4];
endmodule: ripplecarryadder

components/countersyncload/countersyncload.sv
module countersyncload(
  input logic [3:0] D,
  input logic LD,
  input logic clk,
  output logic [3:0] Q
);
  logic [3:0] SA, Y;

  ripplecarryadder rca (
    .A(Q),
    .B(4'd1),
    .CIN(0),
    .S(SA),
    .COUT()
  );

  mux2x4 mux (
    .A(SA),
    .B(D),
    .S(LD),
    .Y(Y)
  );

  dff4 dff (
    .D(Y),
    .clk(clk),
    .Q(Q)
  );

endmodule: countersyncload

components/countersyncload/tb.sv
module tb();
  logic clk;
  logic [3:0] D, Q;
  logic LD;

  countersyncload dut (
    .D(D),
    .Q(Q),
    .LD(LD),
    .clk(clk)
  );

  initial begin
    clk = 0;
    forever #5 clk = !clk;
  end

  initial begin
    LD = 0;
    #120
    LD = 1;
    D = 4'd3;
    #10
    LD = 0;
    #120;
    $finish();
  end

  initial begin
    $dumpfile("dump.vcd");
    $dumpvars;
  end
endmodule: tb

components/countersyncload/dump.vcd
$version Generated by VerilatedVcd $end
$timescale 1ps $end
 $scope module TOP $end
  $scope module tb $end
   $var wire 1 8 clk $end
   $var wire 4 # D [3:0] $end
   $var wire 4 ) Q [3:0] $end
   $var wire 1 $ LD $end
   $scope module dut $end
    $var wire 4 # D [3:0] $end
    $var wire 1 $ LD $end
    $var wire 1 8 clk $end
    $var wire 4 ) Q [3:0] $end
    $var wire 4 * SA [3:0] $end
    $var wire 4 9 Y [3:0] $end
    $scope module dff $end
     $var wire 1 8 clk $end
     $var wire 4 9 D [3:0] $end
     $var wire 4 ) Q [3:0] $end
     $scope module unnamedblk1 $end
      $var wire 32 + i [31:0] $end
     $upscope $end
    $upscope $end
    $scope module mux $end
     $var wire 4 * A [3:0] $end
     $var wire 4 # B [3:0] $end
     $var wire 1 $ S $end
     $var wire 4 9 Y [3:0] $end
     $scope module gen_muxes[0] $end
      $scope module mux $end
       $var wire 1 $ S $end
       $var wire 1 , A $end
       $var wire 1 % B $end
       $var wire 1 : Y $end
      $upscope $end
     $upscope $end
     $scope module gen_muxes[1] $end
      $scope module mux $end
       $var wire 1 $ S $end
       $var wire 1 - A $end
       $var wire 1 & B $end
       $var wire 1 ; Y $end
      $upscope $end
     $upscope $end
     $scope module gen_muxes[2] $end
      $scope module mux $end
       $var wire 1 $ S $end
       $var wire 1 . A $end
       $var wire 1 ' B $end
       $var wire 1 < Y $end
      $upscope $end
     $upscope $end
     $scope module gen_muxes[3] $end
      $scope module mux $end
       $var wire 1 $ S $end
       $var wire 1 / A $end
       $var wire 1 ( B $end
       $var wire 1 = Y $end
      $upscope $end
     $upscope $end
    $upscope $end
    $scope module rca $end
     $var wire 4 ) A [3:0] $end
     $var wire 4 > B [3:0] $end
     $var wire 1 ? CIN $end
     $var wire 4 * S [3:0] $end
     $var wire 1 0 COUT $end
     $var wire 5 1 carry [4:0] $end
     $scope module genblk1[0] $end
      $scope module fa $end
       $var wire 1 2 A $end
       $var wire 1 @ B $end
       $var wire 1 ? CIN $end
       $var wire 1 2 COUT $end
       $var wire 1 , S $end
       $var wire 1 2 COUT1 $end
       $var wire 1 ? COUT2 $end
       $var wire 1 , SUM1 $end
       $scope module ha1 $end
        $var wire 1 2 A $end
        $var wire 1 @ B $end
        $var wire 1 , S $end
        $var wire 1 2 C $end
       $upscope $end
       $scope module ha2 $end
        $var wire 1 , A $end
        $var wire 1 ? B $end
        $var wire 1 , S $end
        $var wire 1 ? C $end
       $upscope $end
      $upscope $end
     $upscope $end
     $scope module genblk1[1] $end
      $scope module fa $end
       $var wire 1 3 A $end
       $var wire 1 ? B $end
       $var wire 1 2 CIN $end
       $var wire 1 4 COUT $end
       $var wire 1 - S $end
       $var wire 1 ? COUT1 $end
       $var wire 1 4 COUT2 $end
       $var wire 1 3 SUM1 $end
       $scope module ha1 $end
        $var wire 1 3 A $end
        $var wire 1 ? B $end
        $var wire 1 3 S $end
        $var wire 1 ? C $end
       $upscope $end
       $scope module ha2 $end
        $var wire 1 3 A $end
        $var wire 1 2 B $end
        $var wire 1 - S $end
        $var wire 1 4 C $end
       $upscope $end
      $upscope $end
     $upscope $end
     $scope module genblk1[2] $end
      $scope module fa $end
       $var wire 1 5 A $end
       $var wire 1 ? B $end
       $var wire 1 4 CIN $end
       $var wire 1 6 COUT $end
       $var wire 1 . S $end
       $var wire 1 ? COUT1 $end
       $var wire 1 6 COUT2 $end
       $var wire 1 5 SUM1 $end
       $scope module ha1 $end
        $var wire 1 5 A $end
        $var wire 1 ? B $end
        $var wire 1 5 S $end
        $var wire 1 ? C $end
       $upscope $end
       $scope module ha2 $end
        $var wire 1 5 A $end
        $var wire 1 4 B $end
        $var wire 1 . S $end
        $var wire 1 6 C $end
       $upscope $end
      $upscope $end
     $upscope $end
     $scope module genblk1[3] $end
      $scope module fa $end
       $var wire 1 7 A $end
       $var wire 1 ? B $end
       $var wire 1 6 CIN $end
       $var wire 1 0 COUT $end
       $var wire 1 / S $end
       $var wire 1 ? COUT1 $end
       $var wire 1 0 COUT2 $end
       $var wire 1 7 SUM1 $end
       $scope module ha1 $end
        $var wire 1 7 A $end
        $var wire 1 ? B $end
        $var wire 1 7 S $end
        $var wire 1 ? C $end
       $upscope $end
       $scope module ha2 $end
        $var wire 1 7 A $end
        $var wire 1 6 B $end
        $var wire 1 / S $end
        $var wire 1 0 C $end
       $upscope $end
      $upscope $end
     $upscope $end
    $upscope $end
   $upscope $end
  $upscope $end
 $upscope $end
$enddefinitions $end


#0
b0000 #
0$
0%
0&
0'
0(
b0000 )
b0001 *
b00000000000000000000000000000000 +
1,
0-
0.
0/
00
b00000 1
02
03
04
05
06
07
08
b0001 9
1:
0;
0<
0=
b0001 >
0?
1@
#5
b0001 )
b0010 *
b00000000000000000000000000000100 +
0,
1-
b00010 1
12
18
b0010 9
0:
1;
#10
08
#15
b0010 )
b0011 *
1,
b00000 1
02
13
18
b0011 9
1:
#20
08
#25
b0011 )
b0100 *
0,
0-
1.
b00110 1
12
14
18
b0100 9
0:
0;
1<
#30
08
#35
b0100 )
b0101 *
1,
b00000 1
02
03
04
15
18
b0101 9
1:
#40
08
#45
b0101 )
b0110 *
0,
1-
b00010 1
12
18
b0110 9
0:
1;
#50
08
#55
b0110 )
b0111 *
1,
b00000 1
02
13
18
b0111 9
1:
#60
08
#65
b0111 )
b1000 *
0,
0-
0.
1/
b01110 1
12
14
16
18
b1000 9
0:
0;
0<
1=
#70
08
#75
b1000 )
b1001 *
1,
b00000 1
02
03
04
05
06
17
18
b1001 9
1:
#80
08
#85
b1001 )
b1010 *
0,
1-
b00010 1
12
18
b1010 9
0:
1;
#90
08
#95
b1010 )
b1011 *
1,
b00000 1
02
13
18
b1011 9
1:
#100
08
#105
b1011 )
b1100 *
0,
0-
1.
b00110 1
12
14
18
b1100 9
0:
0;
1<
#110
08
#115
b1100 )
b1101 *
1,
b00000 1
02
03
04
15
18
b1101 9
1:
#120
b0011 #
1$
1%
1&
08
b0011 9
1;
0<
0=
#125
b0011 )
b0100 *
0,
0/
b00110 1
12
13
14
05
07
18
#130
0$
08
b0100 9
0:
0;
1<
#135
b0100 )
b0101 *
1,
b00000 1
02
03
04
15
18
b0101 9
1:
#140
08
#145
b0101 )
b0110 *
0,
1-
b00010 1
12
18
b0110 9
0:
1;
#150
08
#155
b0110 )
b0111 *
1,
b00000 1
02
13
18
b0111 9
1:
#160
08
#165
b0111 )
b1000 *
0,
0-
0.
1/
b01110 1
12
14
16
18
b1000 9
0:
0;
0<
1=
#170
08
#175
b1000 )
b1001 *
1,
b00000 1
02
03
04
05
06
17
18
b1001 9
1:
#180
08
#185
b1001 )
b1010 *
0,
1-
b00010 1
12
18
b1010 9
0:
1;
#190
08
#195
b1010 )
b1011 *
1,
b00000 1
02
13
18
b1011 9
1:
#200
08
#205
b1011 )
b1100 *
0,
0-
1.
b00110 1
12
14
18
b1100 9
0:
0;
1<
#210
08
#215
b1100 )
b1101 *
1,
b00000 1
02
03
04
15
18
b1101 9
1:
#220
08
#225
b1101 )
b1110 *
0,
1-
b00010 1
12
18
b1110 9
0:
1;
#230
08
#235
b1110 )
b1111 *
1,
b00000 1
02
13
18
b1111 9
1:
#240
08
#245
b1111 )
b0000 *
0,
0-
0.
0/
10
b11110 1
12
14
16
18
b0000 9
0:
0;
0<
0=
